libexec/__init__.py
libexec/exec.py
libexec/files.py
libexec/py.typed
libexec-1.0.1.dist-info/METADATA
libexec-1.0.1.dist-info/WHEEL
libexec-1.0.1.dist-info/licenses/LICENSE
libexec-1.0.1.dist-info/RECORD
