Metadata-Version: 2.4
Name: libexec
Version: 1.0.1
Summary: Run and manipulate files and sysroots in different environments.
Project-URL: Homepage, https://github.com/eLiSCHe/libexec
Author-email: Thomas Irgang <thomas@irgang.eu>
License-File: LICENSE
Classifier: Development Status :: 3 - Alpha
Classifier: License :: OSI Approved :: GNU General Public License v3 (GPLv3)
Classifier: Programming Language :: Python :: 3
Requires-Python: >=3.10
Requires-Dist: pydantic>=2.10.6
